unigbsa/CLI.py
unigbsa/__init__.py
unigbsa/pipeline.py
unigbsa/settings.py
unigbsa/utils.py
unigbsa/version.py
unigbsa/data/default.ini
unigbsa/data/default.json
unigbsa/data/mmpbsa.in
unigbsa/data/scan.json
unigbsa/data/template.json
unigbsa/data/Calibri/Calibri.ttf
unigbsa/data/Calibri/calibribold.ttf
unigbsa/gbsa/__init__.py
unigbsa/gbsa/gbsarun.py
unigbsa/gbsa/io.py
unigbsa/gbsa/parameters.py
unigbsa/gbsa/plots.py
unigbsa/gbsa/utils.py
unigbsa/scanparas/__init__.py
unigbsa/scanparas/scan.py
unigbsa/simulation/__init__.py
unigbsa/simulation/mdrun.py
unigbsa/simulation/openmm-em.py
unigbsa/simulation/topology.py
unigbsa/simulation/utils.py
unigbsa/simulation/mdp/ions.mdp
unigbsa/simulation/mdp/md.mdp
unigbsa/simulation/mdp/mdout.mdp
unigbsa/simulation/mdp/minim.mdp
unigbsa/simulation/mdp/npt.mdp
unigbsa/simulation/mdp/nvt.mdp
unigbsa/simulation/mdp/vaccum.mdp
unigbsa/simulation/mdp/minimization/s1-cg.mdp
unigbsa/simulation/mdp/minimization/s1-steep.mdp
unigbsa/simulation/mdp/minimization/s2-cg.mdp
unigbsa/simulation/mdp/minimization/s2-steep.mdp
unigbsa/simulation/mdp/minimization/s3-steep.mdp
unigbsa/simulation/mdp/minimization/s4-cg.mdp
unigbsa-0.1.7.dist-info/LICENSE.txt
unigbsa-0.1.7.dist-info/METADATA
unigbsa-0.1.7.dist-info/WHEEL
unigbsa-0.1.7.dist-info/entry_points.txt
unigbsa-0.1.7.dist-info/top_level.txt
unigbsa-0.1.7.dist-info/RECORD
