Metadata-Version: 2.1
Name: unigbsa
Version: 0.1.7
Summary: MMPB(GB)SA tools for calculate energy.
Home-page: https://github.com/dptech-corp/Uni-GBSA
Author: dptech.net
Author-email: hermite@dptech.net
Keywords: MMPBSA MMGBSA
License-File: LICENSE.txt
Requires-Dist: acpype
Requires-Dist: gmx-MMPBSA >=1.5.6
Requires-Dist: lickit
Requires-Dist: tqdm
